plumbium/VERSION
plumbium/__init__.py
plumbium/artefacts.py
plumbium/environment.py
plumbium/processresult.py
plumbium/utils.py
plumbium/recorders/__init__.py
plumbium/recorders/csvfile.py
plumbium/recorders/mongodb.py
plumbium/recorders/slack.py
plumbium/recorders/sqldatabase.py
plumbium/recorders/stdout.py
plumbium-0.10.0.dist-info/DESCRIPTION.rst
plumbium-0.10.0.dist-info/METADATA
plumbium-0.10.0.dist-info/RECORD
plumbium-0.10.0.dist-info/WHEEL
plumbium-0.10.0.dist-info/metadata.json
plumbium-0.10.0.dist-info/top_level.txt
plumbium-0.10.0.dist-info/zip-safe
