Metadata-Version: 2.0
Name: plumbium
Version: 0.10.0
Summary: Records the inputs and outputs of scripts
Home-page: https://github.com/jstutters/plumbium
Author: Jon Stutters
Author-email: j.stutters@ucl.ac.uk
License: MIT
Platform: UNKNOWN
Classifier: Development Status :: 4 - Beta
Classifier: Intended Audience :: Science/Research
Classifier: License :: OSI Approved :: MIT License
Classifier: Topic :: System :: Logging
Requires-Dist: wrapt
